cargs/__init__.py
cmdargs/__init__.py
cargs-0.0.1.dist-info/LICENSE
cargs-0.0.1.dist-info/METADATA
cargs-0.0.1.dist-info/WHEEL
cargs-0.0.1.dist-info/top_level.txt
cargs-0.0.1.dist-info/RECORD
