Metadata-Version: 2.1
Name: cargs
Version: 0.0.1
Summary: A commandline arguments parsing Library with an extremely simple interface
Home-page: https://github.com/bombs-kim/cargs
Author: Beomsoo Kim
Author-email: bluewhale8202@gmail.com
License: UNKNOWN
Platform: UNKNOWN
Classifier: Programming Language :: Python :: 3
Classifier: License :: OSI Approved :: MIT License
Classifier: Operating System :: OS Independent
Requires-Python: >=3.6
